LICENSE.md
README.md
git_pusher/__init__.py
git_pusher-0.1.4.dist-info/entry_points.txt
git_pusher-0.1.4.dist-info/LICENSE.md
git_pusher-0.1.4.dist-info/WHEEL
git_pusher-0.1.4.dist-info/METADATA
git_pusher-0.1.4.dist-info/RECORD
