Metadata-Version: 2.1
Name: git-pusher
Version: 0.1.4
Summary: Push files in multiple git repos in one go
Home-page: https://stiliajohny.github.io/python-git-pusher 
License: GPL-3
Keywords: git,multi-push
Author: John Stilia
Author-email: stilia.johny@gmail.com
Requires-Python: >=3.8,<4.0
Classifier: License :: Other/Proprietary License
Classifier: Programming Language :: Python :: 3
Classifier: Programming Language :: Python :: 3.10
Classifier: Programming Language :: Python :: 3.8
Classifier: Programming Language :: Python :: 3.9
Requires-Dist: GitPython (>=3.1.26,<4.0.0)
Requires-Dist: pyfiglet (>=0.8.post1,<0.9)
Project-URL: Repository, https://github.com/stiliajohny/python-git-pusher.git 
